dm_env_wrappers/__init__.py
dm_env_wrappers/dm_env_wrappers_test.py
dm_env_wrappers/py.typed
dm_env_wrappers/_src/action_repeat.py
dm_env_wrappers/_src/base.py
dm_env_wrappers/_src/canonical_spec.py
dm_env_wrappers/_src/concatenate_observations.py
dm_env_wrappers/_src/episode_statistics.py
dm_env_wrappers/_src/episode_statistics_test.py
dm_env_wrappers/_src/expand_scalar_observation_shapes.py
dm_env_wrappers/_src/frame_stacking.py
dm_env_wrappers/_src/gym_wrapper.py
dm_env_wrappers/_src/gym_wrapper_test .py
dm_env_wrappers/_src/gymnasium_wrapper.py
dm_env_wrappers/_src/gymnasium_wrapper_test.py
dm_env_wrappers/_src/lazy_loader.py
dm_env_wrappers/_src/observation_action_reward.py
dm_env_wrappers/_src/single_precision.py
dm_env_wrappers/_src/step_limit.py
dm_env_wrappers/_src/step_limit_test.py
dm_env_wrappers/_src/validate_spec.py
dm_env_wrappers/_src/video.py
dm_env_wrappers/_src/mujoco/action_noise.py
dm_env_wrappers/_src/mujoco/action_smoother.py
dm_env_wrappers/_src/mujoco/dm_control.py
dm_env_wrappers/_src/mujoco/dm_control_video.py
dm_env_wrappers-0.0.13.dist-info/LICENSE
dm_env_wrappers-0.0.13.dist-info/METADATA
dm_env_wrappers-0.0.13.dist-info/WHEEL
dm_env_wrappers-0.0.13.dist-info/top_level.txt
dm_env_wrappers-0.0.13.dist-info/RECORD
